{
	"deploy": {
		"VM:-": {
			"linkReferences": {},
			"autoDeployLib": true
		},
		"main:1": {
			"linkReferences": {},
			"autoDeployLib": true
		},
		"ropsten:3": {
			"linkReferences": {},
			"autoDeployLib": true
		},
		"rinkeby:4": {
			"linkReferences": {},
			"autoDeployLib": true
		},
		"kovan:42": {
			"linkReferences": {},
			"autoDeployLib": true
		},
		"g√∂rli:5": {
			"linkReferences": {},
			"autoDeployLib": true
		},
		"Custom": {
			"linkReferences": {},
			"autoDeployLib": true
		}
	},
	"data": {
		"bytecode": {
			"generatedSources": [],
			"linkReferences": {},
			"object": "610561610026600b82828239805160001a60731461001957fe5b30600052607381538281f3fe73000000000000000000000000000000000000000030146080604052600436106100615760003560e01c80634062fcf9146100665780637cf5c4d6146100ad578063b483a40514610179578063da1efaff146101be578063e62dd287146101f9575b600080fd5b81801561007257600080fd5b506100ab6004803603606081101561008957600080fd5b506001600160a01b0381358116916020810135821691604090910135166102c5565b005b8180156100b957600080fd5b506100ab600480360360608110156100d057600080fd5b6001600160a01b03823581169260208101359091169181019060608101604082013564010000000081111561010457600080fd5b82018360208201111561011657600080fd5b8035906020019184600183028401116401000000008311171561013857600080fd5b91908080601f016020809104026020016040519081016040528093929190818152602001838380828437600092019190915250929550610342945050505050565b81801561018557600080fd5b506100ab6004803603606081101561019c57600080fd5b506001600160a01b0381358116916020810135821691604090910135166103fb565b8180156101ca57600080fd5b506100ab600480360360408110156101e157600080fd5b506001600160a01b038135811691602001351661045b565b81801561020557600080fd5b506100ab6004803603606081101561021c57600080fd5b6001600160a01b03823581169260208101359091169181019060608101604082013564010000000081111561025057600080fd5b82018360208201111561026257600080fd5b8035906020019184600183028401116401000000008311171561028457600080fd5b91908080601f0160208091040260200160405190810160405280939291908181526020018383808284376000920191909152509295506104c6945050505050565b826001600160a01b03166310e96da583836040518363ffffffff1660e01b815260040180836001600160a01b03168152602001826001600160a01b0316815260200192505050600060405180830381600087803b15801561032557600080fd5b505af1158015610339573d6000803e3d6000fd5b50505050505050565b826001600160a01b031663faf78a9a83836040518363ffffffff1660e01b815260040180836001600160a01b0316815260200180602001828103825283818151815260200191508051906020019080838360005b838110156103ae578181015183820152602001610396565b50505050905090810190601f1680156103db5780820380516001836020036101000a031916815260200191505b509350505050600060405180830381600087803b15801561032557600080fd5b826001600160a01b0316635dbe0fb883836040518363ffffffff1660e01b815260040180836001600160a01b03168152602001826001600160a01b0316815260200192505050600060405180830381600087803b15801561032557600080fd5b816001600160a01b031663a30355aa826040518263ffffffff1660e01b815260040180826001600160a01b03168152602001915050600060405180830381600087803b1580156104aa57600080fd5b505af11580156104be573d6000803e3d6000fd5b505050505050565b6040805163ec07c2d160e01b81526001600160a01b038481166024830152600482019283528351604483015283519086169263ec07c2d192859287929182916064909101906020860190808383600083156103ae57818101518382015260200161039656fea26469706673582212201711311c73cadfef230dab3e052b87a975c9ea36f3d071d36ed163383961349364736f6c63430007060033",
			"opcodes": "PUSH2 0x561 PUSH2 0x26 PUSH1 0xB DUP3 DUP3 DUP3 CODECOPY DUP1 MLOAD PUSH1 0x0 BYTE PUSH1 0x73 EQ PUSH2 0x19 JUMPI INVALID JUMPDEST ADDRESS PUSH1 0x0 MSTORE PUSH1 0x73 DUP2 MSTORE8 DUP3 DUP2 RETURN INVALID PUSH20 0x0 ADDRESS EQ PUSH1 0x80 PUSH1 0x40 MSTORE PUSH1 0x4 CALLDATASIZE LT PUSH2 0x61 JUMPI PUSH1 0x0 CALLDATALOAD PUSH1 0xE0 SHR DUP1 PUSH4 0x4062FCF9 EQ PUSH2 0x66 JUMPI DUP1 PUSH4 0x7CF5C4D6 EQ PUSH2 0xAD JUMPI DUP1 PUSH4 0xB483A405 EQ PUSH2 0x179 JUMPI DUP1 PUSH4 0xDA1EFAFF EQ PUSH2 0x1BE JUMPI DUP1 PUSH4 0xE62DD287 EQ PUSH2 0x1F9 JUMPI JUMPDEST PUSH1 0x0 DUP1 REVERT JUMPDEST DUP2 DUP1 ISZERO PUSH2 0x72 JUMPI PUSH1 0x0 DUP1 REVERT JUMPDEST POP PUSH2 0xAB PUSH1 0x4 DUP1 CALLDATASIZE SUB PUSH1 0x60 DUP2 LT ISZERO PUSH2 0x89 JUMPI PUSH1 0x0 DUP1 REVERT JUMPDEST POP PUSH1 0x1 PUSH1 0x1 PUSH1 0xA0 SHL SUB DUP2 CALLDATALOAD DUP2 AND SWAP2 PUSH1 0x20 DUP2 ADD CALLDATALOAD DUP3 AND SWAP2 PUSH1 0x40 SWAP1 SWAP2 ADD CALLDATALOAD AND PUSH2 0x2C5 JUMP JUMPDEST STOP JUMPDEST DUP2 DUP1 ISZERO PUSH2 0xB9 JUMPI PUSH1 0x0 DUP1 REVERT JUMPDEST POP PUSH2 0xAB PUSH1 0x4 DUP1 CALLDATASIZE SUB PUSH1 0x60 DUP2 LT ISZERO PUSH2 0xD0 JUMPI PUSH1 0x0 DUP1 REVERT JUMPDEST PUSH1 0x1 PUSH1 0x1 PUSH1 0xA0 SHL SUB DUP3 CALLDATALOAD DUP2 AND SWAP3 PUSH1 0x20 DUP2 ADD CALLDATALOAD SWAP1 SWAP2 AND SWAP2 DUP2 ADD SWAP1 PUSH1 0x60 DUP2 ADD PUSH1 0x40 DUP3 ADD CALLDATALOAD PUSH5 0x100000000 DUP2 GT ISZERO PUSH2 0x104 JUMPI PUSH1 0x0 DUP1 REVERT JUMPDEST DUP3 ADD DUP4 PUSH1 0x20 DUP3 ADD GT ISZERO PUSH2 0x116 JUMPI PUSH1 0x0 DUP1 REVERT JUMPDEST DUP1 CALLDATALOAD SWAP1 PUSH1 0x20 ADD SWAP2 DUP5 PUSH1 0x1 DUP4 MUL DUP5 ADD GT PUSH5 0x100000000 DUP4 GT OR ISZERO PUSH2 0x138 JUMPI PUSH1 0x0 DUP1 REVERT JUMPDEST SWAP2 SWAP1 DUP1 DUP1 PUSH1 0x1F ADD PUSH1 0x20 DUP1 SWAP2 DIV MUL PUSH1 0x20 ADD PUSH1 0x40 MLOAD SWAP1 DUP2 ADD PUSH1 0x40 MSTORE DUP1 SWAP4 SWAP3 SWAP2 SWAP1 DUP2 DUP2 MSTORE PUSH1 0x20 ADD DUP4 DUP4 DUP1 DUP3 DUP5 CALLDATACOPY PUSH1 0x0 SWAP3 ADD SWAP2 SWAP1 SWAP2 MSTORE POP SWAP3 SWAP6 POP PUSH2 0x342 SWAP5 POP POP POP POP POP JUMP JUMPDEST DUP2 DUP1 ISZERO PUSH2 0x185 JUMPI PUSH1 0x0 DUP1 REVERT JUMPDEST POP PUSH2 0xAB PUSH1 0x4 DUP1 CALLDATASIZE SUB PUSH1 0x60 DUP2 LT ISZERO PUSH2 0x19C JUMPI PUSH1 0x0 DUP1 REVERT JUMPDEST POP PUSH1 0x1 PUSH1 0x1 PUSH1 0xA0 SHL SUB DUP2 CALLDATALOAD DUP2 AND SWAP2 PUSH1 0x20 DUP2 ADD CALLDATALOAD DUP3 AND SWAP2 PUSH1 0x40 SWAP1 SWAP2 ADD CALLDATALOAD AND PUSH2 0x3FB JUMP JUMPDEST DUP2 DUP1 ISZERO PUSH2 0x1CA JUMPI PUSH1 0x0 DUP1 REVERT JUMPDEST POP PUSH2 0xAB PUSH1 0x4 DUP1 CALLDATASIZE SUB PUSH1 0x40 DUP2 LT ISZERO PUSH2 0x1E1 JUMPI PUSH1 0x0 DUP1 REVERT JUMPDEST POP PUSH1 0x1 PUSH1 0x1 PUSH1 0xA0 SHL SUB DUP2 CALLDATALOAD DUP2 AND SWAP2 PUSH1 0x20 ADD CALLDATALOAD AND PUSH2 0x45B JUMP JUMPDEST DUP2 DUP1 ISZERO PUSH2 0x205 JUMPI PUSH1 0x0 DUP1 REVERT JUMPDEST POP PUSH2 0xAB PUSH1 0x4 DUP1 CALLDATASIZE SUB PUSH1 0x60 DUP2 LT ISZERO PUSH2 0x21C JUMPI PUSH1 0x0 DUP1 REVERT JUMPDEST PUSH1 0x1 PUSH1 0x1 PUSH1 0xA0 SHL SUB DUP3 CALLDATALOAD DUP2 AND SWAP3 PUSH1 0x20 DUP2 ADD CALLDATALOAD SWAP1 SWAP2 AND SWAP2 DUP2 ADD SWAP1 PUSH1 0x60 DUP2 ADD PUSH1 0x40 DUP3 ADD CALLDATALOAD PUSH5 0x100000000 DUP2 GT ISZERO PUSH2 0x250 JUMPI PUSH1 0x0 DUP1 REVERT JUMPDEST DUP3 ADD DUP4 PUSH1 0x20 DUP3 ADD GT ISZERO PUSH2 0x262 JUMPI PUSH1 0x0 DUP1 REVERT JUMPDEST DUP1 CALLDATALOAD SWAP1 PUSH1 0x20 ADD SWAP2 DUP5 PUSH1 0x1 DUP4 MUL DUP5 ADD GT PUSH5 0x100000000 DUP4 GT OR ISZERO PUSH2 0x284 JUMPI PUSH1 0x0 DUP1 REVERT JUMPDEST SWAP2 SWAP1 DUP1 DUP1 PUSH1 0x1F ADD PUSH1 0x20 DUP1 SWAP2 DIV MUL PUSH1 0x20 ADD PUSH1 0x40 MLOAD SWAP1 DUP2 ADD PUSH1 0x40 MSTORE DUP1 SWAP4 SWAP3 SWAP2 SWAP1 DUP2 DUP2 MSTORE PUSH1 0x20 ADD DUP4 DUP4 DUP1 DUP3 DUP5 CALLDATACOPY PUSH1 0x0 SWAP3 ADD SWAP2 SWAP1 SWAP2 MSTORE POP SWAP3 SWAP6 POP PUSH2 0x4C6 SWAP5 POP POP POP POP POP JUMP JUMPDEST DUP3 PUSH1 0x1 PUSH1 0x1 PUSH1 0xA0 SHL SUB AND PUSH4 0x10E96DA5 DUP4 DUP4 PUSH1 0x40 MLOAD DUP4 PUSH4 0xFFFFFFFF AND PUSH1 0xE0 SHL DUP2 MSTORE PUSH1 0x4 ADD DUP1 DUP4 PUSH1 0x1 PUSH1 0x1 PUSH1 0xA0 SHL SUB AND DUP2 MSTORE PUSH1 0x20 ADD DUP3 PUSH1 0x1 PUSH1 0x1 PUSH1 0xA0 SHL SUB AND DUP2 MSTORE PUSH1 0x20 ADD SWAP3 POP POP POP PUSH1 0x0 PUSH1 0x40 MLOAD DUP1 DUP4 SUB DUP2 PUSH1 0x0 DUP8 DUP1 EXTCODESIZE ISZERO DUP1 ISZERO PUSH2 0x325 JUMPI PUSH1 0x0 DUP1 REVERT JUMPDEST POP GAS CALL ISZERO DUP1 ISZERO PUSH2 0x339 JUMPI RETURNDATASIZE PUSH1 0x0 DUP1 RETURNDATACOPY RETURNDATASIZE PUSH1 0x0 REVERT JUMPDEST POP POP POP POP POP POP POP JUMP JUMPDEST DUP3 PUSH1 0x1 PUSH1 0x1 PUSH1 0xA0 SHL SUB AND PUSH4 0xFAF78A9A DUP4 DUP4 PUSH1 0x40 MLOAD DUP4 PUSH4 0xFFFFFFFF AND PUSH1 0xE0 SHL DUP2 MSTORE PUSH1 0x4 ADD DUP1 DUP4 PUSH1 0x1 PUSH1 0x1 PUSH1 0xA0 SHL SUB AND DUP2 MSTORE PUSH1 0x20 ADD DUP1 PUSH1 0x20 ADD DUP3 DUP2 SUB DUP3 MSTORE DUP4 DUP2 DUP2 MLOAD DUP2 MSTORE PUSH1 0x20 ADD SWAP2 POP DUP1 MLOAD SWAP1 PUSH1 0x20 ADD SWAP1 DUP1 DUP4 DUP4 PUSH1 0x0 JUMPDEST DUP4 DUP2 LT ISZERO PUSH2 0x3AE JUMPI DUP2 DUP2 ADD MLOAD DUP4 DUP3 ADD MSTORE PUSH1 0x20 ADD PUSH2 0x396 JUMP JUMPDEST POP POP POP POP SWAP1 POP SWAP1 DUP2 ADD SWAP1 PUSH1 0x1F AND DUP1 ISZERO PUSH2 0x3DB JUMPI DUP1 DUP3 SUB DUP1 MLOAD PUSH1 0x1 DUP4 PUSH1 0x20 SUB PUSH2 0x100 EXP SUB NOT AND DUP2 MSTORE PUSH1 0x20 ADD SWAP2 POP JUMPDEST POP SWAP4 POP POP POP POP PUSH1 0x0 PUSH1 0x40 MLOAD DUP1 DUP4 SUB DUP2 PUSH1 0x0 DUP8 DUP1 EXTCODESIZE ISZERO DUP1 ISZERO PUSH2 0x325 JUMPI PUSH1 0x0 DUP1 REVERT JUMPDEST DUP3 PUSH1 0x1 PUSH1 0x1 PUSH1 0xA0 SHL SUB AND PUSH4 0x5DBE0FB8 DUP4 DUP4 PUSH1 0x40 MLOAD DUP4 PUSH4 0xFFFFFFFF AND PUSH1 0xE0 SHL DUP2 MSTORE PUSH1 0x4 ADD DUP1 DUP4 PUSH1 0x1 PUSH1 0x1 PUSH1 0xA0 SHL SUB AND DUP2 MSTORE PUSH1 0x20 ADD DUP3 PUSH1 0x1 PUSH1 0x1 PUSH1 0xA0 SHL SUB AND DUP2 MSTORE PUSH1 0x20 ADD SWAP3 POP POP POP PUSH1 0x0 PUSH1 0x40 MLOAD DUP1 DUP4 SUB DUP2 PUSH1 0x0 DUP8 DUP1 EXTCODESIZE ISZERO DUP1 ISZERO PUSH2 0x325 JUMPI PUSH1 0x0 DUP1 REVERT JUMPDEST DUP2 PUSH1 0x1 PUSH1 0x1 PUSH1 0xA0 SHL SUB AND PUSH4 0xA30355AA DUP3 PUSH1 0x40 MLOAD DUP3 PUSH4 0xFFFFFFFF AND PUSH1 0xE0 SHL DUP2 MSTORE PUSH1 0x4 ADD DUP1 DUP3 PUSH1 0x1 PUSH1 0x1 PUSH1 0xA0 SHL SUB AND DUP2 MSTORE PUSH1 0x20 ADD SWAP2 POP POP PUSH1 0x0 PUSH1 0x40 MLOAD DUP1 DUP4 SUB DUP2 PUSH1 0x0 DUP8 DUP1 EXTCODESIZE ISZERO DUP1 ISZERO PUSH2 0x4AA JUMPI PUSH1 0x0 DUP1 REVERT JUMPDEST POP GAS CALL ISZERO DUP1 ISZERO PUSH2 0x4BE JUMPI RETURNDATASIZE PUSH1 0x0 DUP1 RETURNDATACOPY RETURNDATASIZE PUSH1 0x0 REVERT JUMPDEST POP POP POP POP POP POP JUMP JUMPDEST PUSH1 0x40 DUP1 MLOAD PUSH4 0xEC07C2D1 PUSH1 0xE0 SHL DUP2 MSTORE PUSH1 0x1 PUSH1 0x1 PUSH1 0xA0 SHL SUB DUP5 DUP2 AND PUSH1 0x24 DUP4 ADD MSTORE PUSH1 0x4 DUP3 ADD SWAP3 DUP4 MSTORE DUP4 MLOAD PUSH1 0x44 DUP4 ADD MSTORE DUP4 MLOAD SWAP1 DUP7 AND SWAP3 PUSH4 0xEC07C2D1 SWAP3 DUP6 SWAP3 DUP8 SWAP3 SWAP2 DUP3 SWAP2 PUSH1 0x64 SWAP1 SWAP2 ADD SWAP1 PUSH1 0x20 DUP7 ADD SWAP1 DUP1 DUP4 DUP4 PUSH1 0x0 DUP4 ISZERO PUSH2 0x3AE JUMPI DUP2 DUP2 ADD MLOAD DUP4 DUP3 ADD MSTORE PUSH1 0x20 ADD PUSH2 0x396 JUMP INVALID LOG2 PUSH5 0x6970667358 0x22 SLT KECCAK256 OR GT BALANCE SHR PUSH20 0xCADFEF230DAB3E052B87A975C9EA36F3D071D36E 0xD1 PUSH4 0x38396134 SWAP4 PUSH5 0x736F6C6343 STOP SMOD MOD STOP CALLER ",
			"sourceMap": "738:738:0:-:0;;;;;;;;;;;;;;;;;;;;;;;;;"
		},
		"deployedBytecode": {
			"generatedSources": [],
			"immutableReferences": {},
			"linkReferences": {},
			"object": "73000000000000000000000000000000000000000030146080604052600436106100615760003560e01c80634062fcf9146100665780637cf5c4d6146100ad578063b483a40514610179578063da1efaff146101be578063e62dd287146101f9575b600080fd5b81801561007257600080fd5b506100ab6004803603606081101561008957600080fd5b506001600160a01b0381358116916020810135821691604090910135166102c5565b005b8180156100b957600080fd5b506100ab600480360360608110156100d057600080fd5b6001600160a01b03823581169260208101359091169181019060608101604082013564010000000081111561010457600080fd5b82018360208201111561011657600080fd5b8035906020019184600183028401116401000000008311171561013857600080fd5b91908080601f016020809104026020016040519081016040528093929190818152602001838380828437600092019190915250929550610342945050505050565b81801561018557600080fd5b506100ab6004803603606081101561019c57600080fd5b506001600160a01b0381358116916020810135821691604090910135166103fb565b8180156101ca57600080fd5b506100ab600480360360408110156101e157600080fd5b506001600160a01b038135811691602001351661045b565b81801561020557600080fd5b506100ab6004803603606081101561021c57600080fd5b6001600160a01b03823581169260208101359091169181019060608101604082013564010000000081111561025057600080fd5b82018360208201111561026257600080fd5b8035906020019184600183028401116401000000008311171561028457600080fd5b91908080601f0160208091040260200160405190810160405280939291908181526020018383808284376000920191909152509295506104c6945050505050565b826001600160a01b03166310e96da583836040518363ffffffff1660e01b815260040180836001600160a01b03168152602001826001600160a01b0316815260200192505050600060405180830381600087803b15801561032557600080fd5b505af1158015610339573d6000803e3d6000fd5b50505050505050565b826001600160a01b031663faf78a9a83836040518363ffffffff1660e01b815260040180836001600160a01b0316815260200180602001828103825283818151815260200191508051906020019080838360005b838110156103ae578181015183820152602001610396565b50505050905090810190601f1680156103db5780820380516001836020036101000a031916815260200191505b509350505050600060405180830381600087803b15801561032557600080fd5b826001600160a01b0316635dbe0fb883836040518363ffffffff1660e01b815260040180836001600160a01b03168152602001826001600160a01b0316815260200192505050600060405180830381600087803b15801561032557600080fd5b816001600160a01b031663a30355aa826040518263ffffffff1660e01b815260040180826001600160a01b03168152602001915050600060405180830381600087803b1580156104aa57600080fd5b505af11580156104be573d6000803e3d6000fd5b505050505050565b6040805163ec07c2d160e01b81526001600160a01b038481166024830152600482019283528351604483015283519086169263ec07c2d192859287929182916064909101906020860190808383600083156103ae57818101518382015260200161039656fea26469706673582212201711311c73cadfef230dab3e052b87a975c9ea36f3d071d36ed163383961349364736f6c63430007060033",
			"opcodes": "PUSH20 0x0 ADDRESS EQ PUSH1 0x80 PUSH1 0x40 MSTORE PUSH1 0x4 CALLDATASIZE LT PUSH2 0x61 JUMPI PUSH1 0x0 CALLDATALOAD PUSH1 0xE0 SHR DUP1 PUSH4 0x4062FCF9 EQ PUSH2 0x66 JUMPI DUP1 PUSH4 0x7CF5C4D6 EQ PUSH2 0xAD JUMPI DUP1 PUSH4 0xB483A405 EQ PUSH2 0x179 JUMPI DUP1 PUSH4 0xDA1EFAFF EQ PUSH2 0x1BE JUMPI DUP1 PUSH4 0xE62DD287 EQ PUSH2 0x1F9 JUMPI JUMPDEST PUSH1 0x0 DUP1 REVERT JUMPDEST DUP2 DUP1 ISZERO PUSH2 0x72 JUMPI PUSH1 0x0 DUP1 REVERT JUMPDEST POP PUSH2 0xAB PUSH1 0x4 DUP1 CALLDATASIZE SUB PUSH1 0x60 DUP2 LT ISZERO PUSH2 0x89 JUMPI PUSH1 0x0 DUP1 REVERT JUMPDEST POP PUSH1 0x1 PUSH1 0x1 PUSH1 0xA0 SHL SUB DUP2 CALLDATALOAD DUP2 AND SWAP2 PUSH1 0x20 DUP2 ADD CALLDATALOAD DUP3 AND SWAP2 PUSH1 0x40 SWAP1 SWAP2 ADD CALLDATALOAD AND PUSH2 0x2C5 JUMP JUMPDEST STOP JUMPDEST DUP2 DUP1 ISZERO PUSH2 0xB9 JUMPI PUSH1 0x0 DUP1 REVERT JUMPDEST POP PUSH2 0xAB PUSH1 0x4 DUP1 CALLDATASIZE SUB PUSH1 0x60 DUP2 LT ISZERO PUSH2 0xD0 JUMPI PUSH1 0x0 DUP1 REVERT JUMPDEST PUSH1 0x1 PUSH1 0x1 PUSH1 0xA0 SHL SUB DUP3 CALLDATALOAD DUP2 AND SWAP3 PUSH1 0x20 DUP2 ADD CALLDATALOAD SWAP1 SWAP2 AND SWAP2 DUP2 ADD SWAP1 PUSH1 0x60 DUP2 ADD PUSH1 0x40 DUP3 ADD CALLDATALOAD PUSH5 0x100000000 DUP2 GT ISZERO PUSH2 0x104 JUMPI PUSH1 0x0 DUP1 REVERT JUMPDEST DUP3 ADD DUP4 PUSH1 0x20 DUP3 ADD GT ISZERO PUSH2 0x116 JUMPI PUSH1 0x0 DUP1 REVERT JUMPDEST DUP1 CALLDATALOAD SWAP1 PUSH1 0x20 ADD SWAP2 DUP5 PUSH1 0x1 DUP4 MUL DUP5 ADD GT PUSH5 0x100000000 DUP4 GT OR ISZERO PUSH2 0x138 JUMPI PUSH1 0x0 DUP1 REVERT JUMPDEST SWAP2 SWAP1 DUP1 DUP1 PUSH1 0x1F ADD PUSH1 0x20 DUP1 SWAP2 DIV MUL PUSH1 0x20 ADD PUSH1 0x40 MLOAD SWAP1 DUP2 ADD PUSH1 0x40 MSTORE DUP1 SWAP4 SWAP3 SWAP2 SWAP1 DUP2 DUP2 MSTORE PUSH1 0x20 ADD DUP4 DUP4 DUP1 DUP3 DUP5 CALLDATACOPY PUSH1 0x0 SWAP3 ADD SWAP2 SWAP1 SWAP2 MSTORE POP SWAP3 SWAP6 POP PUSH2 0x342 SWAP5 POP POP POP POP POP JUMP JUMPDEST DUP2 DUP1 ISZERO PUSH2 0x185 JUMPI PUSH1 0x0 DUP1 REVERT JUMPDEST POP PUSH2 0xAB PUSH1 0x4 DUP1 CALLDATASIZE SUB PUSH1 0x60 DUP2 LT ISZERO PUSH2 0x19C JUMPI PUSH1 0x0 DUP1 REVERT JUMPDEST POP PUSH1 0x1 PUSH1 0x1 PUSH1 0xA0 SHL SUB DUP2 CALLDATALOAD DUP2 AND SWAP2 PUSH1 0x20 DUP2 ADD CALLDATALOAD DUP3 AND SWAP2 PUSH1 0x40 SWAP1 SWAP2 ADD CALLDATALOAD AND PUSH2 0x3FB JUMP JUMPDEST DUP2 DUP1 ISZERO PUSH2 0x1CA JUMPI PUSH1 0x0 DUP1 REVERT JUMPDEST POP PUSH2 0xAB PUSH1 0x4 DUP1 CALLDATASIZE SUB PUSH1 0x40 DUP2 LT ISZERO PUSH2 0x1E1 JUMPI PUSH1 0x0 DUP1 REVERT JUMPDEST POP PUSH1 0x1 PUSH1 0x1 PUSH1 0xA0 SHL SUB DUP2 CALLDATALOAD DUP2 AND SWAP2 PUSH1 0x20 ADD CALLDATALOAD AND PUSH2 0x45B JUMP JUMPDEST DUP2 DUP1 ISZERO PUSH2 0x205 JUMPI PUSH1 0x0 DUP1 REVERT JUMPDEST POP PUSH2 0xAB PUSH1 0x4 DUP1 CALLDATASIZE SUB PUSH1 0x60 DUP2 LT ISZERO PUSH2 0x21C JUMPI PUSH1 0x0 DUP1 REVERT JUMPDEST PUSH1 0x1 PUSH1 0x1 PUSH1 0xA0 SHL SUB DUP3 CALLDATALOAD DUP2 AND SWAP3 PUSH1 0x20 DUP2 ADD CALLDATALOAD SWAP1 SWAP2 AND SWAP2 DUP2 ADD SWAP1 PUSH1 0x60 DUP2 ADD PUSH1 0x40 DUP3 ADD CALLDATALOAD PUSH5 0x100000000 DUP2 GT ISZERO PUSH2 0x250 JUMPI PUSH1 0x0 DUP1 REVERT JUMPDEST DUP3 ADD DUP4 PUSH1 0x20 DUP3 ADD GT ISZERO PUSH2 0x262 JUMPI PUSH1 0x0 DUP1 REVERT JUMPDEST DUP1 CALLDATALOAD SWAP1 PUSH1 0x20 ADD SWAP2 DUP5 PUSH1 0x1 DUP4 MUL DUP5 ADD GT PUSH5 0x100000000 DUP4 GT OR ISZERO PUSH2 0x284 JUMPI PUSH1 0x0 DUP1 REVERT JUMPDEST SWAP2 SWAP1 DUP1 DUP1 PUSH1 0x1F ADD PUSH1 0x20 DUP1 SWAP2 DIV MUL PUSH1 0x20 ADD PUSH1 0x40 MLOAD SWAP1 DUP2 ADD PUSH1 0x40 MSTORE DUP1 SWAP4 SWAP3 SWAP2 SWAP1 DUP2 DUP2 MSTORE PUSH1 0x20 ADD DUP4 DUP4 DUP1 DUP3 DUP5 CALLDATACOPY PUSH1 0x0 SWAP3 ADD SWAP2 SWAP1 SWAP2 MSTORE POP SWAP3 SWAP6 POP PUSH2 0x4C6 SWAP5 POP POP POP POP POP JUMP JUMPDEST DUP3 PUSH1 0x1 PUSH1 0x1 PUSH1 0xA0 SHL SUB AND PUSH4 0x10E96DA5 DUP4 DUP4 PUSH1 0x40 MLOAD DUP4 PUSH4 0xFFFFFFFF AND PUSH1 0xE0 SHL DUP2 MSTORE PUSH1 0x4 ADD DUP1 DUP4 PUSH1 0x1 PUSH1 0x1 PUSH1 0xA0 SHL SUB AND DUP2 MSTORE PUSH1 0x20 ADD DUP3 PUSH1 0x1 PUSH1 0x1 PUSH1 0xA0 SHL SUB AND DUP2 MSTORE PUSH1 0x20 ADD SWAP3 POP POP POP PUSH1 0x0 PUSH1 0x40 MLOAD DUP1 DUP4 SUB DUP2 PUSH1 0x0 DUP8 DUP1 EXTCODESIZE ISZERO DUP1 ISZERO PUSH2 0x325 JUMPI PUSH1 0x0 DUP1 REVERT JUMPDEST POP GAS CALL ISZERO DUP1 ISZERO PUSH2 0x339 JUMPI RETURNDATASIZE PUSH1 0x0 DUP1 RETURNDATACOPY RETURNDATASIZE PUSH1 0x0 REVERT JUMPDEST POP POP POP POP POP POP POP JUMP JUMPDEST DUP3 PUSH1 0x1 PUSH1 0x1 PUSH1 0xA0 SHL SUB AND PUSH4 0xFAF78A9A DUP4 DUP4 PUSH1 0x40 MLOAD DUP4 PUSH4 0xFFFFFFFF AND PUSH1 0xE0 SHL DUP2 MSTORE PUSH1 0x4 ADD DUP1 DUP4 PUSH1 0x1 PUSH1 0x1 PUSH1 0xA0 SHL SUB AND DUP2 MSTORE PUSH1 0x20 ADD DUP1 PUSH1 0x20 ADD DUP3 DUP2 SUB DUP3 MSTORE DUP4 DUP2 DUP2 MLOAD DUP2 MSTORE PUSH1 0x20 ADD SWAP2 POP DUP1 MLOAD SWAP1 PUSH1 0x20 ADD SWAP1 DUP1 DUP4 DUP4 PUSH1 0x0 JUMPDEST DUP4 DUP2 LT ISZERO PUSH2 0x3AE JUMPI DUP2 DUP2 ADD MLOAD DUP4 DUP3 ADD MSTORE PUSH1 0x20 ADD PUSH2 0x396 JUMP JUMPDEST POP POP POP POP SWAP1 POP SWAP1 DUP2 ADD SWAP1 PUSH1 0x1F AND DUP1 ISZERO PUSH2 0x3DB JUMPI DUP1 DUP3 SUB DUP1 MLOAD PUSH1 0x1 DUP4 PUSH1 0x20 SUB PUSH2 0x100 EXP SUB NOT AND DUP2 MSTORE PUSH1 0x20 ADD SWAP2 POP JUMPDEST POP SWAP4 POP POP POP POP PUSH1 0x0 PUSH1 0x40 MLOAD DUP1 DUP4 SUB DUP2 PUSH1 0x0 DUP8 DUP1 EXTCODESIZE ISZERO DUP1 ISZERO PUSH2 0x325 JUMPI PUSH1 0x0 DUP1 REVERT JUMPDEST DUP3 PUSH1 0x1 PUSH1 0x1 PUSH1 0xA0 SHL SUB AND PUSH4 0x5DBE0FB8 DUP4 DUP4 PUSH1 0x40 MLOAD DUP4 PUSH4 0xFFFFFFFF AND PUSH1 0xE0 SHL DUP2 MSTORE PUSH1 0x4 ADD DUP1 DUP4 PUSH1 0x1 PUSH1 0x1 PUSH1 0xA0 SHL SUB AND DUP2 MSTORE PUSH1 0x20 ADD DUP3 PUSH1 0x1 PUSH1 0x1 PUSH1 0xA0 SHL SUB AND DUP2 MSTORE PUSH1 0x20 ADD SWAP3 POP POP POP PUSH1 0x0 PUSH1 0x40 MLOAD DUP1 DUP4 SUB DUP2 PUSH1 0x0 DUP8 DUP1 EXTCODESIZE ISZERO DUP1 ISZERO PUSH2 0x325 JUMPI PUSH1 0x0 DUP1 REVERT JUMPDEST DUP2 PUSH1 0x1 PUSH1 0x1 PUSH1 0xA0 SHL SUB AND PUSH4 0xA30355AA DUP3 PUSH1 0x40 MLOAD DUP3 PUSH4 0xFFFFFFFF AND PUSH1 0xE0 SHL DUP2 MSTORE PUSH1 0x4 ADD DUP1 DUP3 PUSH1 0x1 PUSH1 0x1 PUSH1 0xA0 SHL SUB AND DUP2 MSTORE PUSH1 0x20 ADD SWAP2 POP POP PUSH1 0x0 PUSH1 0x40 MLOAD DUP1 DUP4 SUB DUP2 PUSH1 0x0 DUP8 DUP1 EXTCODESIZE ISZERO DUP1 ISZERO PUSH2 0x4AA JUMPI PUSH1 0x0 DUP1 REVERT JUMPDEST POP GAS CALL ISZERO DUP1 ISZERO PUSH2 0x4BE JUMPI RETURNDATASIZE PUSH1 0x0 DUP1 RETURNDATACOPY RETURNDATASIZE PUSH1 0x0 REVERT JUMPDEST POP POP POP POP POP POP JUMP JUMPDEST PUSH1 0x40 DUP1 MLOAD PUSH4 0xEC07C2D1 PUSH1 0xE0 SHL DUP2 MSTORE PUSH1 0x1 PUSH1 0x1 PUSH1 0xA0 SHL SUB DUP5 DUP2 AND PUSH1 0x24 DUP4 ADD MSTORE PUSH1 0x4 DUP3 ADD SWAP3 DUP4 MSTORE DUP4 MLOAD PUSH1 0x44 DUP4 ADD MSTORE DUP4 MLOAD SWAP1 DUP7 AND SWAP3 PUSH4 0xEC07C2D1 SWAP3 DUP6 SWAP3 DUP8 SWAP3 SWAP2 DUP3 SWAP2 PUSH1 0x64 SWAP1 SWAP2 ADD SWAP1 PUSH1 0x20 DUP7 ADD SWAP1 DUP1 DUP4 DUP4 PUSH1 0x0 DUP4 ISZERO PUSH2 0x3AE JUMPI DUP2 DUP2 ADD MLOAD DUP4 DUP3 ADD MSTORE PUSH1 0x20 ADD PUSH2 0x396 JUMP INVALID LOG2 PUSH5 0x6970667358 0x22 SLT KECCAK256 OR GT BALANCE SHR PUSH20 0xCADFEF230DAB3E052B87A975C9EA36F3D071D36E 0xD1 PUSH4 0x38396134 SWAP4 PUSH5 0x736F6C6343 STOP SMOD MOD STOP CALLER ",
			"sourceMap": "738:738:0:-:0;;;;;;;;;;;;;;;;;;;;;;;;;;;;;;;;;;;;;;;;;;;;908:140;;;;;;;;;;;;;;;;;;;;;;;;;;-1:-1:-1;;;;;;908:140:0;;;;;;;;;;;;;;;;;;;:::i;:::-;;1214:136;;;;;;;;;;;;;;;;;;;;;;;;;;-1:-1:-1;;;;;1214:136:0;;;;;;;;;;;;;;;;;;;;;;;;;;;;;;;;;;;;;;;;;;;;;;;;;;;;;;;;;;;;;;;;;;;;;;;;;;;;;;;;;;;;;;;;;;;;;;;;;;;;;;;;;;;;;;;;;;-1:-1:-1;1214:136:0;;-1:-1:-1;1214:136:0;;-1:-1:-1;;;;;1214:136:0:i;1058:146::-;;;;;;;;;;;;;;;;;;;;;;;;;;-1:-1:-1;;;;;;1058:146:0;;;;;;;;;;;;;;;;;;;:::i;1360:114::-;;;;;;;;;;;;;;;;;;;;;;;;;;-1:-1:-1;;;;;;1360:114:0;;;;;;;;;;:::i;772:130::-;;;;;;;;;;;;;;;;;;;;;;;;;;-1:-1:-1;;;;;772:130:0;;;;;;;;;;;;;;;;;;;;;;;;;;;;;;;;;;;;;;;;;;;;;;;;;;;;;;;;;;;;;;;;;;;;;;;;;;;;;;;;;;;;;;;;;;;;;;;;;;;;;;;;;;;;;;;;;;-1:-1:-1;772:130:0;;-1:-1:-1;772:130:0;;-1:-1:-1;;;;;772:130:0:i;908:140::-;1007:4;-1:-1:-1;;;;;995:27:0;;1023:6;1031:9;995:46;;;;;;;;;;;;;-1:-1:-1;;;;;995:46:0;;;;;;-1:-1:-1;;;;;995:46:0;;;;;;;;;;;;;;;;;;;;;;;;;;;;;;;;;;;;;;;;;;;;;;;;;908:140;;;:::o;1214:136::-;1314:4;-1:-1:-1;;;;;1302:26:0;;1329:6;1337:5;1302:41;;;;;;;;;;;;;-1:-1:-1;;;;;1302:41:0;;;;;;;;;;;;;;;;;;;;;;;;;;;;;;;;;;;;;;;;;;;;;;;;;;;;;;;;;;;;;;;;;;;;;;;;;;;;;;;;;;;;;;;;;;;;;;;;;;;;;;;;;;;;;;;;;;;1058:146;1160:4;-1:-1:-1;;;;;1148:30:0;;1179:6;1187:9;1148:49;;;;;;;;;;;;;-1:-1:-1;;;;;1148:49:0;;;;;;-1:-1:-1;;;;;1148:49:0;;;;;;;;;;;;;;;;;;;;;;;;;;;;1360:114;1442:4;-1:-1:-1;;;;;1430:29:0;;1460:6;1430:37;;;;;;;;;;;;;-1:-1:-1;;;;;1430:37:0;;;;;;;;;;;;;;;;;;;;;;;;;;;;;;;;;;;;;;;;;;;;;;;;1360:114;;:::o;772:130::-;856:39;;;-1:-1:-1;;;856:39:0;;-1:-1:-1;;;;;856:39:0;;;;;;;;;;;;;;;;;;;;;:25;;;;;;882:4;;888:6;;856:39;;;;;;;;;;;;;;;-1:-1:-1;856:39:0;;;;;;;;;;;;;;;"
		},
		"gasEstimates": {
			"creation": {
				"codeDepositCost": "275400",
				"executionCost": "343",
				"totalCost": "275743"
			},
			"external": {
				"addFriend(address,address,address)": "infinite",
				"addPhoto(address,address,string)": "infinite",
				"removeFriend(address,address,address)": "infinite",
				"removePhoto(address,address)": "infinite",
				"setName(address,address,string)": "infinite"
			}
		},
		"methodIdentifiers": {
			"addFriend(address,address,address)": "4062fcf9",
			"addPhoto(address,address,string)": "7cf5c4d6",
			"removeFriend(address,address,address)": "b483a405",
			"removePhoto(address,address)": "da1efaff",
			"setName(address,address,string)": "e62dd287"
		}
	},
	"abi": []
}